uztagger/__init__.py
uztagger/lexicon.csv
uztagger/non_affixed_word.csv
uztagger/web-interface-ui.png
uztagger-0.0.11.dist-info/LICENSE
uztagger-0.0.11.dist-info/METADATA
uztagger-0.0.11.dist-info/WHEEL
uztagger-0.0.11.dist-info/top_level.txt
uztagger-0.0.11.dist-info/RECORD
