Metadata-Version: 2.1
Name: uztagger
Version: 0.0.11
Summary: uztagger | Uzbek Morphological Part of Speech (POS) Tagging on Python
Home-page: https://github.com/UlugbekSalaev/uztagger
Author: Ulugbek Salaev
Author-email: ulugbek0302@gmail.com
Project-URL: Bug Tracker, https://github.com/UlugbekSalaev/uztagger/issues
Keywords: mophology,uzbek-language,pos tagging,morphological tagging
Classifier: Programming Language :: Python :: 3
Classifier: License :: OSI Approved :: MIT License
Classifier: Operating System :: OS Independent
Requires-Python: >=3.6
License-File: LICENSE
Requires-Dist: UzMorphAnalyser
Requires-Dist: pandas
